ai_management/__init__.py
ai_management/config.yaml
ai_management/constants.py
ai_management/main.py
ai_management/model_evaluation.py
examples/usage_examples.ipynb
src/ai_management/__init__.py
src/ai_management/constants.py
src/ai_management/main.py
ai_management-1.0.40.dist-info/LICENSE.txt
ai_management-1.0.40.dist-info/METADATA
ai_management-1.0.40.dist-info/WHEEL
ai_management-1.0.40.dist-info/top_level.txt
ai_management-1.0.40.dist-info/RECORD
