Metadata-Version: 2.1
Name: ai-management
Version: 1.0.40
Summary: This is a toolbox to help AI & ML teams to have a better management of their metrics.
Home-page: https://github.com/adeo/aim
Author: Leroy Merlin Brazil
Author-email: chapter_inteligencia_artificia@leroymerlin.com.br
License: MIT
Project-URL: Bug Tracker, https://github.com/adeo/aim/issues
Keywords: management,toolbox,lmbr,ai
Platform: UNKNOWN
Classifier: Development Status :: 2 - Pre-Alpha
Classifier: Intended Audience :: Developers
Classifier: Topic :: Software Development :: Documentation
Classifier: License :: OSI Approved :: MIT License
Classifier: Programming Language :: Python :: 3.7
License-File: LICENSE.txt
Requires-Dist: pandas (>=1.0.4)
Requires-Dist: numpy (>=1.20.0)
Requires-Dist: scikit-learn (>=1.0.0)
Requires-Dist: google-cloud-bigquery (>=2.34.4)
